mcp_server_browser/__init__.py
mcp_server_browser/app.py
mcp_server_browser/config.py
mcp_server_browser/message.py
mcp_server_browser/mcp_server/__init__.py
mcp_server_browser/mcp_server/mcp.py
mcp_server_browser/mcp_server/tool_util.py
mcp_server_browser/mcp_server/types.py
mcp_server_browser/websockets_services/__init__.py
mcp_server_browser/websockets_services/connection_manager.py
mcp_server_browser/websockets_services/message_pool.py
mcp_server_browser/websockets_services/websocket_server.py
mcp_server_browser-0.1.0.dist-info/METADATA
mcp_server_browser-0.1.0.dist-info/WHEEL
mcp_server_browser-0.1.0.dist-info/entry_points.txt
mcp_server_browser-0.1.0.dist-info/RECORD
